hackerlib
qlib
