Metadata-Version: 1.0
Name: Mroylib
Version: 1.3.0
Summary: a steady version
Home-page: https://git.oschina.net/dark.h/Mroylib.git
Author: Qing luan
Author-email: darkhackdevil@gmail.com
License: MIT
Platform: UNKNOWN
